pydata_factory/__init__.py
pydata_factory/classes.py
pydata_factory/config.py
pydata_factory/data.py
pydata_factory/schema.py
pydata_factory/utils.py
pydata_factory-0.1.7.dist-info/LICENSE
pydata_factory-0.1.7.dist-info/METADATA
pydata_factory-0.1.7.dist-info/WHEEL
pydata_factory-0.1.7.dist-info/top_level.txt
pydata_factory-0.1.7.dist-info/RECORD
