Metadata-Version: 2.1
Name: pydata-factory
Version: 0.1.7
Summary: Create data for testing from data files.
Home-page: https://github.com/osl-incubator/pydata_factory
Author: Ivan Ogasawara
Author-email: ivan.ogasawara@gmail.com
License: MIT license
Keywords: pydata_factory
Platform: UNKNOWN
Classifier: Development Status :: 2 - Pre-Alpha
Classifier: Intended Audience :: Developers
Classifier: License :: OSI Approved :: MIT License
Classifier: Natural Language :: English
Classifier: Programming Language :: Python :: 3
Classifier: Programming Language :: Python :: 3.6
Classifier: Programming Language :: Python :: 3.7
Classifier: Programming Language :: Python :: 3.8
License-File: LICENSE
Requires-Dist: factory-boy
Requires-Dist: pandas
Requires-Dist: pyarrow
Requires-Dist: sqlalchemy
Provides-Extra: dev
Requires-Dist: factory-boy ; extra == 'dev'
Requires-Dist: pandas ; extra == 'dev'
Requires-Dist: pyarrow ; extra == 'dev'
Requires-Dist: sqlalchemy ; extra == 'dev'
